LICENSE.txt
MANIFEST.in
README.rst
icanhasfile.py
setup.cfg
setup.py
icanhasfile.egg-info/PKG-INFO
icanhasfile.egg-info/SOURCES.txt
icanhasfile.egg-info/dependency_links.txt
icanhasfile.egg-info/entry_points.txt
icanhasfile.egg-info/requires.txt
icanhasfile.egg-info/top_level.txt