Metadata-Version: 1.1
Name: icanhasfile
Version: 0.1.0
Summary: COMPUTR, U HAS FILE. I CAN HAS IT?
Home-page: http://artloder.com/code/icanhasfile/
Author: Arthur Loder
Author-email: art@artloder.com
License: MIT
Platform: UNKNOWN
Classifier: Development Status :: 4 - Beta
Classifier: Environment :: Console
Classifier: License :: OSI Approved :: MIT License
Classifier: Operating System :: OS Independent
Classifier: Topic :: Utilities
